<?xml version="1.0" encoding="UTF-8"?>
<SpRL>
 <SCENE>
  <SENTENCE id="s1" indicator="SPEECHACT" type="SA_TELL" PUNCTYPE="DECL" start="0" end="63">
   <TEXT>in the background there is a table with school equipment on it .</TEXT>
   <RELATION id="1" head="V405572" res="V405273" label="CONTENT"/>
   <PHRASE id="V405273" indicator="F" type="EXISTS" text="BE" TENSE="PRES" start="0" end="63"/>
   <RELATION id="2" head="V405273" res="V405325" label="NEUTRAL"/>
   <RELATION id="3" head="V405273" res="V405197" label="LOCATION"/>
   <PHRASE id="V405197" indicator="F" type="IN-LOC" text="IN" start="0" end="18"/>
   <RELATION id="4" head="V405197" res="V405253" label="GROUND"/>
   <RELATION id="5" head="V405197" res="V405273" label="FIGURE"/>
   <PHRASE id="V405253" indicator="THE" type="IMAGE" text="BACKGROUND" start="3" end="18"/>
   <PHRASE id="V405260" indicator="PRO" type="EXPLETIVE" PROFORM="THERE" start="18" end="24"/>
   <PHRASE id="V405325" indicator="A" type="TABLE" text="TABLE" start="27" end="63"/>
   <RELATION id="6" head="V405325" res="V405331" label="MOD"/>
   <PHRASE id="V405331" indicator="F" type="ASSOC-WITH" text="WITH" start="35" end="63"/>
   <RELATION id="7" head="V405331" res="V405346" label="GROUND"/>
   <RELATION id="8" head="V405331" res="V405325" label="FIGURE"/>
   <PHRASE id="V405346" indicator="BARE" type="FUNCTIONAL-PHYS-OBJECT" text="EQUIPMENT" start="40" end="63"/>
   <RELATION id="9" head="V405346" res="V405343" label="ASSOC-WITH"/>
   <RELATION id="10" head="V405346" res="V405354" label="LOCATION"/>
   <PHRASE id="V405343" indicator="KIND" type="ACADEMIC-INSTITUTION" text="SCHOOL" start="40" end="63"/>
   <PHRASE id="V405354" indicator="F" type="ON" text="ON" start="57" end="63"/>
   <RELATION id="11" head="V405354" res="V405376" label="GROUND"/>
   <RELATION id="12" head="V405354" res="V405346" label="FIGURE"/>
   <PHRASE id="V405376" indicator="PRO" type="REFERENTIAL-SEM" text="IT" PROFORM="IT" start="60" end="63"/>
   <RELATION id="13" head="V405376" res="V405253" label="COREF"/>
  </SENTENCE>
 </SCENE>
</SpRL>
