<?xml version="1.0" encoding="UTF-8"?>
<SpRL>
 <SCENE>
  <SENTENCE id="s1" indicator="F" type="MODIFIER" text="DARK-PUNC-MINUS-SKINNED" start="2" end="15" WNSENSE="dark-skinned%5:00:00">
   <TEXT>dark-skinned ,</TEXT>
  </SENTENCE>
  <SENTENCE id="s2" indicator="BARE" type="FEMALE-CHILD" text="GIRL" start="17" end="36">
   <TEXT>dark-haired girl , w</TEXT>
   <RELATION id="1" head="V350661" res="V350658" label="MOD"/>
   <PHRASE id="V350658" indicator="F" type="MODIFIER" text="DARK-PUNC-MINUS-HAIRED" start="17" end="29" WNSENSE="dark-haired%5:00:00"/>
   <RELATION id="2" head="V350658" res="V350661" label="FIGURE"/>
  </SENTENCE>
  <SENTENCE id="s3" indicator="SPEECHACT" type="SA_TELL" PUNCTYPE="DECL" start="36" end="102">
   <TEXT>wearing a skirt and a dark vest , is standing in front of a house .</TEXT>
   <RELATION id="3" head="V352053" res="V350797" label="CONTENT"/>
   <PHRASE id="V350797" indicator="F" type="BE" text="BE" TENSE="PRES" start="36" end="102"/>
   <RELATION id="4" head="V350797" res="V350670" label="NEUTRAL"/>
   <RELATION id="5" head="V350797" res="V350814" label="NEUTRAL1"/>
   <PHRASE id="V350670" indicator="BARE" type="WEAR" text="WEAR" start="36" end="70"/>
   <RELATION id="6" head="V350670" res="V350727" label="NEUTRAL"/>
   <PHRASE id="V350727" indicator="INDEF-SET" type="ATTIRE" OPERATOR="AND" start="44" end="68"/>
   <RELATION id="7" head="V350727" res="V350720" label="SEQUENCE"/>
   <RELATION id="8" head="V350727" res="V350785" label="SEQUENCE1"/>
   <PHRASE id="V350720" indicator="A" type="ATTIRE" text="SKIRT" start="44" end="52"/>
   <PHRASE id="V350785" indicator="A" type="ATTIRE" text="VEST" start="56" end="68"/>
   <RELATION id="9" head="V350785" res="V350777" label="MOD"/>
   <PHRASE id="V350777" indicator="F" type="DARK-VAL" text="DARK" start="58" end="63"/>
   <RELATION id="10" head="V350777" res="V350785" label="FIGURE"/>
   <PHRASE id="V350814" indicator="BARE" type="BE-AT-LOC" text="STAND" start="73" end="102"/>
   <RELATION id="11" head="V350814" res="V350823" label="LOCATION"/>
   <PHRASE id="V350823" indicator="F" type="IN-LOC" text="IN" start="82" end="102"/>
   <RELATION id="12" head="V350823" res="V350884" label="GROUND"/>
   <RELATION id="13" head="V350823" res="V350814" label="FIGURE"/>
   <PHRASE id="V350884" indicator="BARE" type="OBJECT-DEPENDENT-LOCATION" text="FRONT" start="85" end="102"/>
   <RELATION id="14" head="V350884" res="V350989" label="FIGURE"/>
   <PHRASE id="V350989" indicator="A" type="LODGING" text="HOUSE" start="91" end="102"/>
  </SENTENCE>
 </SCENE>
</SpRL>
