<?xml version="1.0" encoding="UTF-8"?>
<SpRL>
 <SCENE>
  <SENTENCE id="s1" indicator="INDEF-SET" type="PHYS-OBJECT" OPERATOR="AND" start="0" end="37">
   <TEXT>a little red wooden desk and two red a</TEXT>
   <RELATION id="1" head="V152080" res="V152076" label="SEQUENCE"/>
   <RELATION id="2" head="V152080" res="V152100" label="SEQUENCE1"/>
   <PHRASE id="V152076" indicator="A" type="FURNISHINGS" text="DESK" start="0" end="25"/>
   <RELATION id="3" head="V152076" res="V152011" label="MOD"/>
   <RELATION id="4" head="V152076" res="V152062" label="MOD"/>
   <RELATION id="5" head="V152076" res="V152070" label="MOD"/>
   <PHRASE id="V152011" indicator="F" type="LITTLE" text="LITTLE" ORIENTATION="LESS" INTENSITY="MED" SCALE="SIZE-SCALE" start="2" end="9"/>
   <RELATION id="6" head="V152011" res="V152076" label="FIGURE"/>
   <PHRASE id="V152062" indicator="F" type="RED" text="RED" SCALE="COLOR-SCALE" start="9" end="13"/>
   <RELATION id="7" head="V152062" res="V152076" label="FIGURE"/>
   <PHRASE id="V152070" indicator="F" type="AWKWARD-VAL" text="WOODEN" start="13" end="20"/>
   <RELATION id="8" head="V152070" res="V152076" label="FIGURE"/>
   <PHRASE id="V152100" indicator="BARE" type="PERSON" text="RED" start="29" end="37"/>
   <RELATION id="9" head="V152100" res="V152090" label="ASSOC-WITH"/>
   <PHRASE id="V152090" indicator="THE" type="TIME-LOC" NAME-OF="(TWO)" HOUR="2" start="29" end="33"/>
  </SENTENCE>
  <SENTENCE id="s2" indicator="SPEECHACT" type="SA_IDENTIFY" start="37" end="82">
   <TEXT>and two blue chairs in front of a green wall f</TEXT>
   <RELATION id="10" head="V152653" res="V152126" label="CONTENT"/>
   <RELATION id="11" head="V152653" res="V152109" label="MOD"/>
   <PHRASE id="V152109" indicator="F" type="CONJUNCT" text="AND" start="37" end="41"/>
   <RELATION id="12" head="V152109" res="V152653" label="FIGURE"/>
   <PHRASE id="V152126" indicator="INDEF-SET" type="FURNISHINGS" text="CHAIR" start="41" end="82"/>
   <RELATION id="13" head="V152126" res="V152118" label="SIZE"/>
   <RELATION id="14" head="V152126" res="V152133" label="LOCATION"/>
   <RELATION id="15" head="V152126" res="V152120" label="MOD"/>
   <PHRASE id="V152118" indicator="A" type="NUMBER" VALUE="2" start="41" end="45"/>
   <PHRASE id="V152120" indicator="F" type="BLUE" text="BLUE" SCALE="COLOR-SCALE" start="45" end="50"/>
   <RELATION id="16" head="V152120" res="V152126" label="FIGURE"/>
   <PHRASE id="V152133" indicator="F" type="IN-LOC" text="IN" start="57" end="82"/>
   <RELATION id="17" head="V152133" res="V152182" label="GROUND"/>
   <RELATION id="18" head="V152133" res="V152126" label="FIGURE"/>
   <PHRASE id="V152182" indicator="BARE" type="OBJECT-DEPENDENT-LOCATION" text="FRONT" start="60" end="82"/>
   <RELATION id="19" head="V152182" res="V152295" label="FIGURE"/>
   <PHRASE id="V152295" indicator="A" type="STRUCTURE-INTERNAL-COMPONENT" text="WALL" start="66" end="82"/>
   <RELATION id="20" head="V152295" res="V152284" label="MOD"/>
   <PHRASE id="V152284" indicator="F" type="GREEN" text="GREEN" SCALE="GREEN*1--07--00" start="71" end="77"/>
   <RELATION id="21" head="V152284" res="V152295" label="FIGURE"/>
  </SENTENCE>
  <SENTENCE id="s3" indicator="F" type="FULL" text="FULL" start="82" end="113">
   <TEXT>full with children's paintings .</TEXT>
   <RELATION id="22" head="V152300" res="V152307" label="MOD"/>
   <PHRASE id="V152307" indicator="F" type="ASSOC-WITH" text="WITH" start="87" end="113"/>
   <RELATION id="23" head="V152307" res="V152372" label="GROUND"/>
   <PHRASE id="V152372" indicator="THE" type="REFERENTIAL-SEM" text="PAINTINGS" start="92" end="113"/>
   <RELATION id="24" head="V152372" res="V152319" label="ASSOC-POSS"/>
   <RELATION id="25" head="V152372" res="V152118" label="COREF"/>
   <PHRASE id="V152319" indicator="INDEF-SET" type="CHILD" text="CHILD" start="92" end="100"/>
  </SENTENCE>
 </SCENE>
</SpRL>
