<?xml version="1.0" encoding="UTF-8"?>
<SpRL>
 <SCENE>
  <SENTENCE id="s1" indicator="SPEECHACT" type="SA_TELL" PUNCTYPE="DECL" start="0" end="54">
   <TEXT>one of the workers is sitting and talking to the kids .</TEXT>
   <RELATION id="1" head="V258966" res="V258283" label="CONTENT"/>
   <PHRASE id="V258283" indicator="F" type="EVENT-OF-ACTION" OPERATOR="AND" TENSE="PRES" PROGR="+" start="0" end="54"/>
   <RELATION id="2" head="V258283" res="V258144" label="SEQUENCE"/>
   <RELATION id="3" head="V258283" res="V258167" label="SEQUENCE1"/>
   <PHRASE id="V258167" indicator="F" type="TALK" text="TALK" start="0" end="54"/>
   <RELATION id="4" head="V258167" res="V258095" label="AGENT"/>
   <RELATION id="5" head="V258167" res="V258213" label="AGENT1"/>
   <PHRASE id="V258144" indicator="F" type="BODY-MOVEMENT-PLACE" text="SIT" start="0" end="54"/>
   <RELATION id="6" head="V258144" res="V258095" label="AGENT"/>
   <PHRASE id="V258095" indicator="BARE" type="REFERENTIAL-SEM" text="ONE" start="0" end="19"/>
   <RELATION id="7" head="V258095" res="V258103" label="MOD"/>
   <PHRASE id="V258103" indicator="F" type="CONTAIN-RELN" text="OF" start="4" end="19"/>
   <RELATION id="8" head="V258103" res="V258116" label="GROUND"/>
   <RELATION id="9" head="V258103" res="V258095" label="FIGURE"/>
   <PHRASE id="V258116" indicator="THE-SET" type="PROFESSIONAL" text="WORKER" start="7" end="19"/>
   <PHRASE id="V258213" indicator="THE-SET" type="CHILD" text="KID" start="42" end="54"/>
  </SENTENCE>
 </SCENE>
</SpRL>
